LICENSE
MANIFEST.in
README.md
setup.py
src/wheezy/__init__.py
src/wheezy.web.egg-info/PKG-INFO
src/wheezy.web.egg-info/SOURCES.txt
src/wheezy.web.egg-info/dependency_links.txt
src/wheezy.web.egg-info/namespace_packages.txt
src/wheezy.web.egg-info/not-zip-safe
src/wheezy.web.egg-info/requires.txt
src/wheezy.web.egg-info/top_level.txt
src/wheezy/web/__init__.py
src/wheezy/web/authorization.py
src/wheezy/web/caching.py
src/wheezy/web/templates.py
src/wheezy/web/transforms.py
src/wheezy/web/handlers/__init__.py
src/wheezy/web/handlers/base.py
src/wheezy/web/handlers/file.py
src/wheezy/web/handlers/method.py
src/wheezy/web/handlers/template.py
src/wheezy/web/middleware/__init__.py
src/wheezy/web/middleware/bootstrap.py
src/wheezy/web/middleware/errors.py
src/wheezy/web/middleware/routing.py